pynxtools_mpes/__init__.py
pynxtools_mpes/mkdocs.py
pynxtools_mpes/reader.py
pynxtools_mpes/nomad/entrypoints.py
pynxtools_mpes/nomad/examples/E1 Convert to NeXus.ipynb
pynxtools_mpes/nomad/examples/E2 ARPES postprocessing.ipynb
pynxtools_mpes/nomad/examples/E3 pyARPES analysis.ipynb
pynxtools_mpes/nomad/examples/E4 Convert to k-space.ipynb
pynxtools_mpes/nomad/examples/MoTe.archive.json
pynxtools_mpes/nomad/examples/README.md
pynxtools_mpes/nomad/examples/WSe2.archive.json
pynxtools_mpes/nomad/examples/WSe2_eln.yaml
pynxtools_mpes/nomad/examples/config_file.json
pynxtools_mpes/nomad/examples/downloads.archive.yaml
pynxtools_mpes/nomad/examples/eln_data.yaml
pynxtools_mpes/nomad/examples/mpes.scheme.archive.yml
pynxtools_mpes/nomad/examples/sed_config/mpes_example_config.yaml
pynxtools_mpes-0.2.6.dist-info/METADATA
pynxtools_mpes-0.2.6.dist-info/WHEEL
pynxtools_mpes-0.2.6.dist-info/entry_points.txt
pynxtools_mpes-0.2.6.dist-info/top_level.txt
pynxtools_mpes-0.2.6.dist-info/RECORD
